pymctp_exerciser_serial/__init__.py
pymctp_exerciser_serial/tty_serial.py
pymctp_exerciser_serial-0.2.5.dist-info/METADATA
pymctp_exerciser_serial-0.2.5.dist-info/WHEEL
pymctp_exerciser_serial-0.2.5.dist-info/entry_points.txt
pymctp_exerciser_serial-0.2.5.dist-info/RECORD
