Metadata-Version: 2.4
Name: pymctp-exerciser-serial
Version: 0.2.5
Summary: TTY/Serial port exerciser for pymctp
Project-URL: Documentation, https://github.com/jls5177/pymctp#readme
Project-URL: Issues, https://github.com/jls5177/pymctp/issues
Project-URL: Source, https://github.com/jls5177/pymctp
Author-email: Justin Simon <justin@simonctl.com>
License: MIT
Keywords: mctp,serial,tty,uart
Classifier: Development Status :: 4 - Beta
Classifier: Intended Audience :: Developers
Classifier: Programming Language :: Python
Classifier: Programming Language :: Python :: 3.8
Classifier: Programming Language :: Python :: 3.9
Classifier: Programming Language :: Python :: 3.10
Classifier: Programming Language :: Python :: 3.11
Classifier: Programming Language :: Python :: 3.12
Classifier: Programming Language :: Python :: Implementation :: CPython
Classifier: Topic :: Software Development :: Libraries
Classifier: Topic :: System :: Hardware
Requires-Python: >=3.8
Requires-Dist: pymctp>=0.2.5
Requires-Dist: pyserial
